sqlchemistry
