Metadata-Version: 1.0
Name: SQLChemistry
Version: 0.0.1rc2
Summary: SQLChemistry helps create SQLAlchemy objects from .ini configuration files parsed by ConfigObj
Home-page: UNKNOWN
Author: Emanuel Gardaya Calso
Author-email: egcalso@gmail.com
License: LGPL
Keywords: config sql
Platform: UNKNOWN
